jcci/__init__.py
jcci/analyze.py
jcci/config.py
jcci/constant.py
jcci/database.py
jcci/diff_parse.py
jcci/graph.py
jcci/java_parse.py
jcci/mapper_parse.py
jcci/sql.py
jcci-0.2.1.dist-info/LICENSE
jcci-0.2.1.dist-info/METADATA
jcci-0.2.1.dist-info/WHEEL
jcci-0.2.1.dist-info/top_level.txt
jcci-0.2.1.dist-info/RECORD
