Metadata-Version: 2.1
Name: jcci
Version: 0.2.1
Summary: Java code commit impact, java code change impact analysis, java代码改动影响范围分析工具
Author-email: Oliver Li <441640312@qq.com>
License: Apache License
Project-URL: Homepage, https://github.com/baikaishuipp/jcci
Project-URL: Bug Tracker, https://github.com/baikaishuipp/jcci/issues
Classifier: Programming Language :: Python :: 3
Classifier: License :: OSI Approved :: Apache Software License
Classifier: Operating System :: OS Independent
Requires-Python: >=3.9
License-File: LICENSE
Requires-Dist: javalang >=0.13.0
Requires-Dist: unidiff >=0.7.4
